README.rst
bootstrap.py
buildout.cfg
setup.py
docs/HISTORY.txt
docs/INSTALL.txt
docs/LICENSE.GPL
docs/LICENSE.txt
zopyx/__init__.py
zopyx.together.egg-info/PKG-INFO
zopyx.together.egg-info/SOURCES.txt
zopyx.together.egg-info/dependency_links.txt
zopyx.together.egg-info/entry_points.txt
zopyx.together.egg-info/namespace_packages.txt
zopyx.together.egg-info/not-zip-safe
zopyx.together.egg-info/requires.txt
zopyx.together.egg-info/top_level.txt
zopyx/together/__init__.py
zopyx/together/configure.zcml
zopyx/together/interfaces.py
zopyx/together/browser/__init__.py
zopyx/together/browser/configure.zcml
zopyx/together/browser/controlpanel.py
zopyx/together/browser/viewlet.pt
zopyx/together/browser/viewlet.py
zopyx/together/profiles/default/controlpanel.xml
zopyx/together/profiles/default/jsregistry.xml
zopyx/together/profiles/default/metadata.xml
zopyx/together/profiles/default/registry.xml
zopyx/together/profiles/default/viewlets.xml
zopyx/together/together/__init__.py
zopyx/together/together/configure.zcml
zopyx/together/together/tests.py
zopyx/together/together/version.txt