Metadata-Version: 1.1
Name: zopyx.together
Version: 0.2.1
Summary: Plone integration with together.js
Home-page: http://github.com/zopyx/zopyx.together
Author: Andreas Jung
Author-email: info@zopyx.com
License: GPL
Keywords: Plone TogetherJS
Platform: UNKNOWN
Classifier: Framework :: Plone
Classifier: Programming Language :: Python
